setup.py
arpit_probability_distribution_2020/Binomialdistribution.py
arpit_probability_distribution_2020/Gaussiandistribution.py
arpit_probability_distribution_2020/Generaldistribution.py
arpit_probability_distribution_2020/__init__.py
arpit_probability_distribution_2020.egg-info/PKG-INFO
arpit_probability_distribution_2020.egg-info/SOURCES.txt
arpit_probability_distribution_2020.egg-info/dependency_links.txt
arpit_probability_distribution_2020.egg-info/not-zip-safe
arpit_probability_distribution_2020.egg-info/top_level.txt