Metadata-Version: 1.0
Name: arpit-probability-distribution-2020
Version: 0.1
Summary: Gaussian and Binomial distributions
Home-page: UNKNOWN
Author: Arpit Maheshwari
Author-email: arpitmaheshwari14@gmail.com
License: UNKNOWN
Platform: UNKNOWN
